[
  {
    "ContainingType": "AuthController",
    "Method": "Login",
    "RelativePath": "api/Auth/login",
    "HttpMethod": "POST",
    "IsController": true,
    "Order": 0,
    "Parameters": [
      {
        "Name": "request",
        "Type": "Crud.MODELS.ENTITY.UserDto",
        "IsRequired": true
      }
    ],
    "ReturnTypes": []
  },
  {
    "ContainingType": "AuthController",
    "Method": "Signup",
    "RelativePath": "api/Auth/signup",
    "HttpMethod": "POST",
    "IsController": true,
    "Order": 0,
    "Parameters": [
      {
        "Name": "request",
        "Type": "Crud.MODELS.ENTITY.UserDto",
        "IsRequired": true
      }
    ],
    "ReturnTypes": []
  },
  {
    "ContainingType": "Crud.Controllers.ReviewsController",
    "Method": "GetAllReviews",
    "RelativePath": "api/Reviews/all-reviews",
    "HttpMethod": "GET",
    "IsController": true,
    "Order": 0,
    "Parameters": [
      {
        "Name": "page",
        "Type": "System.Int32",
        "IsRequired": false
      },
      {
        "Name": "pageSize",
        "Type": "System.Int32",
        "IsRequired": false
      },
      {
        "Name": "location",
        "Type": "System.String",
        "IsRequired": false
      },
      {
        "Name": "sentiment",
        "Type": "System.String",
        "IsRequired": false
      },
      {
        "Name": "rating",
        "Type": "System.Nullable\u00601[[System.Int32, System.Private.CoreLib, Version=8.0.0.0, Culture=neutral, PublicKeyToken=7cec85d7bea7798e]]",
        "IsRequired": false
      }
    ],
    "ReturnTypes": []
  },
  {
    "ContainingType": "Crud.Controllers.ReviewsController",
    "Method": "GetLocations",
    "RelativePath": "api/Reviews/locations",
    "HttpMethod": "GET",
    "IsController": true,
    "Order": 0,
    "Parameters": [],
    "ReturnTypes": []
  },
  {
    "ContainingType": "Crud.Controllers.ReviewsController",
    "Method": "SubmitReview",
    "RelativePath": "api/Reviews/submit",
    "HttpMethod": "POST",
    "IsController": true,
    "Order": 0,
    "Parameters": [
      {
        "Name": "dto",
        "Type": "Crud.MODELS.NewReviewDto",
        "IsRequired": true
      }
    ],
    "ReturnTypes": []
  },
  {
    "ContainingType": "Crud.Controllers.WeatherForecastController",
    "Method": "Get",
    "RelativePath": "WeatherForecast",
    "HttpMethod": "GET",
    "IsController": true,
    "Order": 0,
    "Parameters": [],
    "ReturnTypes": [
      {
        "Type": "System.Collections.Generic.IEnumerable\u00601[[Crud.WeatherForecast, Crud, Version=1.0.0.0, Culture=neutral, PublicKeyToken=null]]",
        "MediaTypes": [
          "text/plain",
          "application/json",
          "text/json"
        ],
        "StatusCode": 200
      }
    ],
    "EndpointName": "GetWeatherForecast"
  }
]